wsogram/__init__.py
wsogram/dispatcher.py
wsogram/exceptions.py
wsogram/filters.py
wsogram/router.py
wsogram/server.py
wsogram/websocket.py
wsogram/middleware/__init__.py
wsogram/types/__init__.py
wsogram-0.0.2.dist-info/licenses/LICENSE
wsogram-0.0.2.dist-info/METADATA
wsogram-0.0.2.dist-info/WHEEL
wsogram-0.0.2.dist-info/top_level.txt
wsogram-0.0.2.dist-info/RECORD
